[
  {
    "tab_name": "Normal Examples",
    "examples": [
      {
        "name": "standard",
        "expressions": [
          {
            "value": "John plays football or chess"
          },
          {
            "value": "When it is raining, John plays not football"
          },
          {
            "value": "It is raining"
          }
        ],
        "to_be_shown": "John plays not football"
      }
    ]
  },
  {
    "tab_name": "Syllogism",
    "examples": [
      {
        "name": "Philospher Examaple",
        "expressions": [
          {
            "value": "all persons are mortal"
          },
          {
            "value": "all philosophers are persons"
          }
        ],
        "to_be_shown": "all philosophers are mortal"
      },
      {
        "name": "Greeks are Mortal",
        "expressions": [
          {
            "value": "All humans are mortal"
          },
          {
            "value": "All Greeks are human"
          }
        ],
        "to_be_shown": "Therefore, all greeks are mortal"
      }
    ]
  },
  {
    "tab_name": "My cool new tab",
    "examples": [
      {
        "name": "My first example",
        "expressions": [
          {
            "value": "no humans are birds"
          },
          {
            "value": "Sam is a human"
          }
        ],
        "to_be_shown": "Sam is not a bird"
      },
      {
        "name": " 2",
        "expressions": [
          {
            "value": "all persons are mortal"
          },
          {
            "value": "all philosophers are persons"
          }
        ],
        "to_be_shown": "all philosophers are mortal"
      }
    ]
  }
]
